LICENSE.txt
MANIFEST.in
README.rst
setup.py
dxf2svg/__init__.py
dxf2svg/__main__.py
dxf2svg/pycore.py
dxf2svg.egg-info/PKG-INFO
dxf2svg.egg-info/SOURCES.txt
dxf2svg.egg-info/dependency_links.txt
dxf2svg.egg-info/requires.txt
dxf2svg.egg-info/top_level.txt