Metadata-Version: 2.1
Name: dxf2svg
Version: 0.1.3
Summary: Dxf to svg converter
Home-page: https://bitbucket.org/lukaszlaba/dxf2svg
Author: Lukasz Laba
Author-email: lukaszlaba@gmail.com
License: GNU General Public License (GPL)
Keywords: dxf,svg
Classifier: Development Status :: 3 - Alpha
Classifier: Environment :: X11 Applications :: Qt
Classifier: Intended Audience :: End Users/Desktop
Classifier: License :: OSI Approved :: GNU General Public License (GPL)
Classifier: Operating System :: POSIX :: Linux
Classifier: Operating System :: Microsoft :: Windows
Classifier: Programming Language :: Python
Classifier: Topic :: Multimedia :: Graphics :: Graphics Conversion
Requires-Python: >=3.5, <4
License-File: LICENSE.txt
